quickmap/__init__.py
quickmap/quickmap.py
quickmap-1.0.1.dist-info/LICENSE
quickmap-1.0.1.dist-info/METADATA
quickmap-1.0.1.dist-info/WHEEL
quickmap-1.0.1.dist-info/top_level.txt
quickmap-1.0.1.dist-info/RECORD
