Metadata-Version: 2.1
Name: quickmap
Version: 1.0.1
Summary: Quick and Simple Class-to-Dict Mapping for Python using decorators
Home-page: https://github.com/roymanigley/QuickMap
Author: Roy Manigley
Author-email: roy.manigley@gmail.com
License: MIT
Classifier: Development Status :: 5 - Production/Stable
Classifier: Intended Audience :: Developers
Classifier: License :: OSI Approved :: MIT License
Classifier: Operating System :: POSIX :: Linux
Classifier: Programming Language :: Python :: 3.10
License-File: LICENSE
